msensorapi/__init__.py
msensorapi/example_main.py
msensorapi/make_proto.py
msensorapi/sim_adapter.py
msensorapi/lib/__init__.py
msensorapi/protobuf/__init__.py
msensorapi/protobuf/morai_actor_pb2.py
msensorapi/protobuf/morai_actor_pb2_grpc.py
msensorapi/protobuf/morai_mgeo_pb2.py
msensorapi/protobuf/morai_mgeo_pb2_grpc.py
msensorapi/protobuf/morai_sensor_pb2.py
msensorapi/protobuf/morai_sensor_pb2_grpc.py
msensorapi/protobuf/morai_sim_info_pb2.py
msensorapi/protobuf/morai_sim_info_pb2_grpc.py
msensorapi/protobuf/morai_simulation_pb2.py
msensorapi/protobuf/morai_simulation_pb2_grpc.py
msensorapi/protobuf/morai_type_pb2.py
msensorapi/protobuf/morai_type_pb2_grpc.py
msensorapi-0.0.1.dist-info/METADATA
msensorapi-0.0.1.dist-info/WHEEL
msensorapi-0.0.1.dist-info/top_level.txt
msensorapi-0.0.1.dist-info/RECORD
